video2live/__init__.py
video2live/__main__.py
video2live/cli.py
video2live-0.0.7.dist-info/METADATA
video2live-0.0.7.dist-info/WHEEL
video2live-0.0.7.dist-info/entry_points.txt
video2live-0.0.7.dist-info/top_level.txt
video2live-0.0.7.dist-info/RECORD
