Metadata-Version: 2.2
Name: video2live
Version: 0.0.7
Summary: Convert videos to iOS Live Photos
Home-page: https://github.com/sherlockouo/video2live
Author: SherlockOuO
Author-email: wdf.coder@gmail.com
Classifier: Programming Language :: Python :: 3
Classifier: License :: OSI Approved :: MIT License
Classifier: Operating System :: OS Independent
Requires-Python: >=3.8
Requires-Dist: moviepy>=2.1.1
Requires-Dist: imageio>=2.37.0
Requires-Dist: Pillow>=10.1.0
Requires-Dist: imageio-ffmpeg>=0.6.0
Requires-Dist: makelive>=0.6.2
Dynamic: author
Dynamic: author-email
Dynamic: classifier
Dynamic: description
Dynamic: description-content-type
Dynamic: home-page
Dynamic: requires-dist
Dynamic: requires-python
Dynamic: summary
